{
"goalscorers" : [
    {
        "Name": "Robin van Persie",
        "goals": "11",
        "country": "Netherlands"
    },
    {
        "Name": "Deon McCauly",
        "goals": "11",
        "country": "Belize"
    },
    {
        "Name": "Luis Suárez",
        "goals": "11",
        "country": "Uruguay"
    },
    {
        "Name": "Lionel Messi",
        "goals": "10",
        "country": "Argentina"
    },
    {
        "Name": "Peter Byers",
        "goals": "10",
        "country": ""
    },
    {
        "Name": "Edin Džeko",
        "goals": "10",
        "country": "Bosnia-Herzegnovia"
    },
    {
        "Name": "Oribe Peralta",
        "goals": "10",
        "country": "Mexico"
    },
    {
        "Name": "Blas Pérez",
        "goals": "10",
        "country": "Panama"
    },
    {
        "Name": "Gonzalo Higuaín",
        "goals": "9",
        "country": "Argentina"
    },
    {
        "Name": "Radamel Falcao",
        "goals": "9",
        "country": "Colombia"
    },
    {
        "Name": "Jerry Bengtson",
        "goals": "9",
        "country": "Honduras"
    },
    {
        "Name": "Vedad Ibišević",
        "goals": "8",
        "country": "Bosnia-Herzegnovia"
    },
    {
        "Name": "Álvaro Saborío",
        "goals": "8",
        "country": "Costa Rica"
    },
    {
        "Name": "Mesut Özil",
        "goals": "8",
        "country": "Germany"
    },
    {
        "Name": "Shinji Okazaki",
        "goals": "8",
        "country": "Japan"
    },
    {
        "Name": "Georges Gope-Fenepej",
        "goals": "8",
        "country": "New Caledonia"
    },
    {
        "Name": "Cristiano Ronaldo",
        "goals": "8",
        "country": "Portugal"
    },
    {
        "Name": "Zlatan Ibrahimović",
        "goals": "8",
        "country": "Sweden"
    },
    {
        "Name": "Clint Dempsey",
        "goals": "8",
        "country": "United States"
    }
],
"goals" : [
    {
        "team": "Netherlands",
        "scored": "32"
    },
    {
        "team": "Germany",
        "scored": "31"
    },
    {
        "team": "England",
        "scored": "29"
    },
    {
        "team": "Bosnia-Herzegnovia",
        "scored": "29"
    },
    {
        "team": "Ukraine",
        "scored": "20"
    },
    {
        "team": "Russia",
        "scored": "19"
    },
    {
        "team": "Hungary",
        "scored": "19"
    },
    {
        "team": "Poland",
        "scored": "18"
    },
    {
        "team": "Israel",
        "scored": "18"
    }
],
"sessions" : [
    {
        "date": "June 1, 2014",
        "number": "0",
        "num": "7"
    },
    {
        "date": "June 2, 2014",
        "number": "1",
        "num": "16"
    },
    {
        "date": "June 3, 2014",
        "number": "0",
        "num": "15"
    },
    {
        "date": "June 4, 2014",
        "number": "1",
        "num": "16"
    },
    {
        "date": "June 5, 2014",
        "number": "6",
        "num": "21"
    },
    {
        "date": "June 6, 2014",
        "number": "1",
        "num": "18"
    },
    {
        "date": "June 7, 2014",
        "number": "0",
        "num": "8"
    },
    {
        "date": "June 8, 2014",
        "number": "0",
        "num": "10"
    },
    {
        "date": "June 9, 2014",
        "number": "2",
        "num": "17"
    },
    {
        "date": "June 10, 2014",
        "number": "2",
        "num": "17"
    },
    {
        "date": "June 11, 2014",
        "number": "1",
        "num": "14"
    },
    {
        "date": "June 12, 2014",
        "number": "1",
        "num": "16"
    },
    {
        "date": "June 13, 2014",
        "number": "2",
        "num": "17"
    },
    {
        "date": "June 14, 2014",
        "number": "3",
        "num": "20"
    },
    {
        "date": "June 15, 2014",
        "number": "1",
        "num": "6"
    },
    {
        "date": "June 16, 2014",
        "number": "1",
        "num": "7"
    }
],
"locale" : [
    {
        "country": "New Zealand",
        "visitors": "41",
        "percentage": "65"
    },
    {
        "country": "United States",
        "visitors": "10",
        "percentage": "16"
    },
    {
        "country": "Brazil",
        "visitors": "5",
        "percentage": "8"
    },
    {
        "country": "France",
        "visitors": "2",
        "percentage": "3"
    },
    {
        "country": "India",
        "visitors": "2",
        "percentage": "3"
    },
    {
        "country": "Chile",
        "visitors": "1",
        "percentage": "2"
    },
    {
        "country": "Spain",
        "visitors": "1",
        "percentage": "2"
    },
    {
        "country": "Russia",
        "visitors": "1",
        "percentage": "2"
    }
]
}
